{
  "Routes": [
    // Group
    {
      "DownstreamPathTemplate": "/api/Group/GetAllGroup",
      "DownstreamScheme": "http",
      "DownstreamHostAndPorts": [
        {
          "Host": "educenter.api",
          "Port": 80
        }
      ],
      "UpstreamPathTemplate": "/allGroup",
      "UpstreamHttpMethod": [ "Get" ]
    },
    {
      "DownstreamPathTemplate": "/api/Group/CreateGroup",
      "DownstreamScheme": "http",
      "DownstreamHostAndPorts": [
        {
          "Host": "educenter.api",
          "Port": 80
        }
      ],
      "UpstreamPathTemplate": "/createGroup",
      "UpstreamHttpMethod": [ "Post" ]
    },
    {
      "DownstreamPathTemplate": "/api/Group/DeleteById?id={Id}",
      "DownstreamScheme": "http",
      "DownstreamHostAndPorts": [
        {
          "Host": "educenter.api",
          "Port": 80
        }
      ],
      "UpstreamPathTemplate": "/deleteIdGroup/{Id}",
      "UpstreamHttpMethod": [ "Delete" ]
    },
    {
      "DownstreamPathTemplate": "/api/Group/GetGroupById?id={Id}",
      "DownstreamScheme": "http",
      "DownstreamHostAndPorts": [
        {
          "Host": "educenter.api",
          "Port": 80
        }
      ],
      "UpstreamPathTemplate": "/getIdGroup/{Id}",
      "UpstreamHttpMethod": [ "Get" ]
    },
    {
      "DownstreamPathTemplate": "/api/Group/UpdateGroup",
      "DownstreamScheme": "http",
      "DownstreamHostAndPorts": [
        {
          "Host": "educenter.api",
          "Port": 80
        }
      ],
      "UpstreamPathTemplate": "/updateGroup",
      "UpstreamHttpMethod": [ "Put" ]
    },


    //Room

    {
      "DownstreamPathTemplate": "/api/Room/GetAllRoom",
      "DownstreamScheme": "http",
      "DownstreamHostAndPorts": [
        {
          "Host": "educenter.api",
          "Port": 80
        }
      ],
      "UpstreamPathTemplate": "/allRoom",
      "UpstreamHttpMethod": [ "Get" ]
    },
    {
      "DownstreamPathTemplate": "/api/Room/CreateRoom",
      "DownstreamScheme": "http",
      "DownstreamHostAndPorts": [
        {
          "Host": "educenter.api",
          "Port": 80
        }
      ],
      "UpstreamPathTemplate": "/createRoom",
      "UpstreamHttpMethod": [ "Post" ]
    },
    {
      "DownstreamPathTemplate": "/api/Room/DeleteById?id={Id}",
      "DownstreamScheme": "http",
      "DownstreamHostAndPorts": [
        {
          "Host": "educenter.api",
          "Port": 80
        }
      ],
      "UpstreamPathTemplate": "/deleteIdRoom/{Id}",
      "UpstreamHttpMethod": [ "Delete" ]
    },
    {
      "DownstreamPathTemplate": "/api/Room/GetRoomById?id={Id}",
      "DownstreamScheme": "http",
      "DownstreamHostAndPorts": [
        {
          "Host": "educenter.api",
          "Port": 80
        }
      ],
      "UpstreamPathTemplate": "/getIdRoom/{Id}",
      "UpstreamHttpMethod": [ "Get" ]
    },
    {
      "DownstreamPathTemplate": "/api/Room/UpdateRoom",
      "DownstreamScheme": "http",
      "DownstreamHostAndPorts": [
        {
          "Host": "educenter.api",
          "Port": 80
        }
      ],
      "UpstreamPathTemplate": "/updateRoom",
      "UpstreamHttpMethod": [ "Put" ]
    },

    // School

    {
      "DownstreamPathTemplate": "/api/School/GetAllSchool",
      "DownstreamScheme": "http",
      "DownstreamHostAndPorts": [
        {
          "Host": "educenter.api",
          "Port": 80
        }
      ],
      "UpstreamPathTemplate": "/allSchool",
      "UpstreamHttpMethod": [ "Get" ]
    },
    {
      "DownstreamPathTemplate": "/api/School/CreateSchool",
      "DownstreamScheme": "http",
      "DownstreamHostAndPorts": [
        {
          "Host": "educenter.api",
          "Port": 80
        }
      ],
      "UpstreamPathTemplate": "/createSchool",
      "UpstreamHttpMethod": [ "Post" ]
    },
    {
      "DownstreamPathTemplate": "/api/School/DeleteById?id={Id}",
      "DownstreamScheme": "http",
      "DownstreamHostAndPorts": [
        {
          "Host": "educenter.api",
          "Port": 80
        }
      ],
      "UpstreamPathTemplate": "/deleteIdSchool/{Id}",
      "UpstreamHttpMethod": [ "Delete" ]
    },
    {
      "DownstreamPathTemplate": "/api/Group/GetSchoolById?id={Id}",
      "DownstreamScheme": "http",
      "DownstreamHostAndPorts": [
        {
          "Host": "educenter.api",
          "Port": 80
        }
      ],
      "UpstreamPathTemplate": "/getIdSchool/{Id}",
      "UpstreamHttpMethod": [ "Get" ]
    },
    {
      "DownstreamPathTemplate": "/api/School/UpdateSchool",
      "DownstreamScheme": "http",
      "DownstreamHostAndPorts": [
        {
          "Host": "educenter.api",
          "Port": 80
        }
      ],
      "UpstreamPathTemplate": "/updateSchool",
      "UpstreamHttpMethod": [ "Put" ]
    },

    //Student

    {
      "DownstreamPathTemplate": "/api/Student/GetAllStudent",
      "DownstreamScheme": "http",
      "DownstreamHostAndPorts": [
        {
          "Host": "educenter.api",
          "Port": 80
        }
      ],
      "UpstreamPathTemplate": "/allStudent",
      "UpstreamHttpMethod": [ "Get" ]
    },
    {
      "DownstreamPathTemplate": "/api/Student/CreateStudent",
      "DownstreamScheme": "http",
      "DownstreamHostAndPorts": [
        {
          "Host": "educenter.api",
          "Port": 80
        }
      ],
      "UpstreamPathTemplate": "/createStudent",
      "UpstreamHttpMethod": [ "Post" ]
    },
    {
      "DownstreamPathTemplate": "/api/Student/DeleteById?id={Id}",
      "DownstreamScheme": "http",
      "DownstreamHostAndPorts": [
        {
          "Host": "educenter.api",
          "Port": 80
        }
      ],
      "UpstreamPathTemplate": "/deleteIdStudent/{Id}",
      "UpstreamHttpMethod": [ "Delete" ]
    },
    {
      "DownstreamPathTemplate": "/api/Student/GetGroupById?id={Id}",
      "DownstreamScheme": "http",
      "DownstreamHostAndPorts": [
        {
          "Host": "educenter.api",
          "Port": 80
        }
      ],
      "UpstreamPathTemplate": "/getIdStudent/{Id}",
      "UpstreamHttpMethod": [ "Get" ]
    },
    {
      "DownstreamPathTemplate": "/api/Student/UpdateStudent",
      "DownstreamScheme": "http",
      "DownstreamHostAndPorts": [
        {
          "Host": "educenter.api",
          "Port": 80
        }
      ],
      "UpstreamPathTemplate": "/updateStudent",
      "UpstreamHttpMethod": [ "Put" ]
    },

    // Teacher

    {
      "DownstreamPathTemplate": "/api/Teacher/GetAllTeacher",
      "DownstreamScheme": "http",
      "DownstreamHostAndPorts": [
        {
          "Host": "educenter.api",
          "Port": 80
        }
      ],
      "UpstreamPathTemplate": "/allTeacher",
      "UpstreamHttpMethod": [ "Get" ]
    },
    {
      "DownstreamPathTemplate": "/api/Teacher/CreateTeacher",
      "DownstreamScheme": "http",
      "DownstreamHostAndPorts": [
        {
          "Host": "educenter.api",
          "Port": 80
        }
      ],
      "UpstreamPathTemplate": "/createTeacher",
      "UpstreamHttpMethod": [ "Post" ]
    },
    {
      "DownstreamPathTemplate": "/api/Teacher/DeleteById?id={Id}",
      "DownstreamScheme": "http",
      "DownstreamHostAndPorts": [
        {
          "Host": "educenter.api",
          "Port": 80
        }
      ],
      "UpstreamPathTemplate": "/deleteIdTeacher/{Id}",
      "UpstreamHttpMethod": [ "Delete" ]
    },
    {
      "DownstreamPathTemplate": "/api/Group/GetTeacherById?id={Id}",
      "DownstreamScheme": "http",
      "DownstreamHostAndPorts": [
        {
          "Host": "educenter.api",
          "Port": 80
        }
      ],
      "UpstreamPathTemplate": "/getIdTeacher/{Id}",
      "UpstreamHttpMethod": [ "Get" ]
    },
    {
      "DownstreamPathTemplate": "/api/Teacher/UpdateTeacher",
      "DownstreamScheme": "http",
      "DownstreamHostAndPorts": [
        {
          "Host": "educenter.api",
          "Port": 80
        }
      ],
      "UpstreamPathTemplate": "/updateTeacher",
      "UpstreamHttpMethod": [ "Put" ]
    },



    // Team

    {
      "DownstreamPathTemplate": "/api/Team/GetAllTeam",
      "DownstreamScheme": "http",
      "DownstreamHostAndPorts": [
        {
          "Host": "sport.api",
          "Port": 80
        }
      ],
      "UpstreamPathTemplate": "/allTeam",
      "UpstreamHttpMethod": [ "Get" ]
    },
    {
      "DownstreamPathTemplate": "/api/Team/CreateTeam",
      "DownstreamScheme": "http",
      "DownstreamHostAndPorts": [
        {
          "Host": "sport.api",
          "Port": 80
        }
      ],
      "UpstreamPathTemplate": "/createTeam",
      "UpstreamHttpMethod": [ "Post" ]
    },
    {
      "DownstreamPathTemplate": "/api/Team/DeleteById?id={Id}",
      "DownstreamScheme": "http",
      "DownstreamHostAndPorts": [
        {
          "Host": "sport.api",
          "Port": 80
        }
      ],
      "UpstreamPathTemplate": "/deleteIdTeam/{Id}",
      "UpstreamHttpMethod": [ "Delete" ]
    },
    {
      "DownstreamPathTemplate": "/api/Team/GetTeamById?id={Id}",
      "DownstreamScheme": "http",
      "DownstreamHostAndPorts": [
        {
          "Host": "sport.api",
          "Port": 80
        }
      ],
      "UpstreamPathTemplate": "/getIdTeam/{Id}",
      "UpstreamHttpMethod": [ "Get" ]
    },
    {
      "DownstreamPathTemplate": "/api/Team/UpdateTeam",
      "DownstreamScheme": "http",
      "DownstreamHostAndPorts": [
        {
          "Host": "sport.api",
          "Port": 80
        }
      ],
      "UpstreamPathTemplate": "/updateTeam",
      "UpstreamHttpMethod": [ "Put" ]
    },

    // Player

    {
      "DownstreamPathTemplate": "/api/Player/GetAllPlayer",
      "DownstreamScheme": "http",
      "DownstreamHostAndPorts": [
        {
          "Host": "sport.api",
          "Port": 80
        }
      ],
      "UpstreamPathTemplate": "/allPlayer",
      "UpstreamHttpMethod": [ "Get" ]
    },
    {
      "DownstreamPathTemplate": "/api/Player/CreatePlayer",
      "DownstreamScheme": "http",
      "DownstreamHostAndPorts": [
        {
          "Host": "sport.api",
          "Port": 80
        }
      ],
      "UpstreamPathTemplate": "/createPlayer",
      "UpstreamHttpMethod": [ "Post" ]
    },
    {
      "DownstreamPathTemplate": "/api/Player/DeleteById?id={Id}",
      "DownstreamScheme": "http",
      "DownstreamHostAndPorts": [
        {
          "Host": "sport.api",
          "Port": 80
        }
      ],
      "UpstreamPathTemplate": "/deleteIdPlayer/{Id}",
      "UpstreamHttpMethod": [ "Delete" ]
    },
    {
      "DownstreamPathTemplate": "/api/Player/GetPlayerById?id={Id}",
      "DownstreamScheme": "http",
      "DownstreamHostAndPorts": [
        {
          "Host": "sport.api",
          "Port": 80
        }
      ],
      "UpstreamPathTemplate": "/getIdPlayer/{Id}",
      "UpstreamHttpMethod": [ "Get" ]
    },
    {
      "DownstreamPathTemplate": "/api/Player/UpdatePlayer",
      "DownstreamScheme": "http",
      "DownstreamHostAndPorts": [
        {
          "Host": "sport.api",
          "Port": 80
        }
      ],
      "UpstreamPathTemplate": "/updatePlayer",
      "UpstreamHttpMethod": [ "Put" ]
    },

    // Order

    {
      "DownstreamPathTemplate": "/api/Order/GetAllOrder",
      "DownstreamScheme": "http",
      "DownstreamHostAndPorts": [
        {
          "Host": "sport.api",
          "Port": 80
        }
      ],
      "UpstreamPathTemplate": "/allOrder",
      "UpstreamHttpMethod": [ "Get" ]
    },
    {
      "DownstreamPathTemplate": "/api/Player/CreateOrder",
      "DownstreamScheme": "http",
      "DownstreamHostAndPorts": [
        {
          "Host": "sport.api",
          "Port": 80
        }
      ],
      "UpstreamPathTemplate": "/createOrder",
      "UpstreamHttpMethod": [ "Post" ]
    },
    {
      "DownstreamPathTemplate": "/api/Order/DeleteById?id={Id}",
      "DownstreamScheme": "http",
      "DownstreamHostAndPorts": [
        {
          "Host": "sport.api",
          "Port": 80
        }
      ],
      "UpstreamPathTemplate": "/deleteIdOrder/{Id}",
      "UpstreamHttpMethod": [ "Delete" ]
    },
    {
      "DownstreamPathTemplate": "/api/Player/GetOrderById?id={Id}",
      "DownstreamScheme": "http",
      "DownstreamHostAndPorts": [
        {
          "Host": "sport.api",
          "Port": 80
        }
      ],
      "UpstreamPathTemplate": "/getIdOrder/{Id}",
      "UpstreamHttpMethod": [ "Get" ]
    },
    {
      "DownstreamPathTemplate": "/api/Order/UpdateOrder",
      "DownstreamScheme": "http",
      "DownstreamHostAndPorts": [
        {
          "Host": "sport.api",
          "Port": 80
        }
      ],
      "UpstreamPathTemplate": "/updateOrder",
      "UpstreamHttpMethod": [ "Put" ]
    },


    // Coach

    {
      "DownstreamPathTemplate": "/api/Coach/GetAllCoach",
      "DownstreamScheme": "http",
      "DownstreamHostAndPorts": [
        {
          "Host": "sport.api",
          "Port": 80
        }
      ],
      "UpstreamPathTemplate": "/allCoach",
      "UpstreamHttpMethod": [ "Get" ]
    },
    {
      "DownstreamPathTemplate": "/api/Coach/CreateCoach",
      "DownstreamScheme": "http",
      "DownstreamHostAndPorts": [
        {
          "Host": "sport.api",
          "Port": 80
        }
      ],
      "UpstreamPathTemplate": "/createCoach",
      "UpstreamHttpMethod": [ "Post" ]
    },
    {
      "DownstreamPathTemplate": "/api/Coach/DeleteById?id={Id}",
      "DownstreamScheme": "http",
      "DownstreamHostAndPorts": [
        {
          "Host": "sport.api",
          "Port": 80
        }
      ],
      "UpstreamPathTemplate": "/deleteIdCoach/{Id}",
      "UpstreamHttpMethod": [ "Delete" ]
    },
    {
      "DownstreamPathTemplate": "/api/Coach/GetCoachById?id={Id}",
      "DownstreamScheme": "http",
      "DownstreamHostAndPorts": [
        {
          "Host": "sport.api",
          "Port": 80
        }
      ],
      "UpstreamPathTemplate": "/getIdCoach/{Id}",
      "UpstreamHttpMethod": [ "Get" ]
    },
    {
      "DownstreamPathTemplate": "/api/Player/UpdateCoach",
      "DownstreamScheme": "http",
      "DownstreamHostAndPorts": [
        {
          "Host": "sport.api",
          "Port": 80
        }
      ],
      "UpstreamPathTemplate": "/updateCoach",
      "UpstreamHttpMethod": [ "Put" ]
    }

  ],
  "GlobalConfiguration": {
    "BaseUrl": "https://localhost:5000"
  }
}